centralized_data/__init__.py
centralized_data/_asset_loader.py
centralized_data/_singleton.py
centralized_data/py.typed
centralized_data-0.0.4.dist-info/METADATA
centralized_data-0.0.4.dist-info/WHEEL
centralized_data-0.0.4.dist-info/licenses/LICENSE
centralized_data-0.0.4.dist-info/RECORD
