Metadata-Version: 2.4
Name: centralized_data
Version: 0.0.4
Summary: Package for cantralized-data, such as singletons, bindable singletons, global collections, dynamically loaded objects  in Python.
Project-URL: Homepage, https://github.com/Snowcaloid/py-centralized-data
Project-URL: Issues, https://github.com/Snowcaloid/py-centralized-data/issues
Author-email: Snowcaloid <dev.snowcaloid@gmail.com>
License-File: LICENSE
Classifier: Operating System :: OS Independent
Classifier: Programming Language :: Python :: 3
Requires-Python: >=3.13.2
Requires-Dist: pyyaml>=6.0.2
